ttr/aws/utils/s3/__init__.py
ttr/aws/utils/s3/cli/__init__.py
ttr/aws/utils/s3/cli/chart.html
ttr/aws/utils/s3/cli/getvers.py
ttr/aws/utils/s3/cli/lsvers.py
ttr/aws/utils/s3/cli/tmpgen.py
ttr/aws/utils/s3/saver.py
ttr/aws/utils/s3/utils.py
ttr_aws_utils_s3-0.6.1.dist-info/METADATA
ttr_aws_utils_s3-0.6.1.dist-info/WHEEL
ttr_aws_utils_s3-0.6.1.dist-info/entry_points.txt
ttr_aws_utils_s3-0.6.1.dist-info/licenses/AUTHORS
ttr_aws_utils_s3-0.6.1.dist-info/licenses/LICENSE.rst
ttr_aws_utils_s3-0.6.1.dist-info/RECORD
