Metadata-Version: 2.1
Name: ttr.aws.utils.s3
Version: 0.6.1
Summary: CLI to list and fetch objects from versioned S3 buckets. Plus get tmp url.
Keywords: aws s3
Home-page: https://gitlab.com/tamtamresearch-public/pypi/ttr.aws.utils.s3
Author: Jan Vlcinsky
Author-Email: Unknown <jan.vlcinsky@tamtamresearch.com>
License: BSD
Project-URL: Homepage, https://gitlab.com/tamtamresearch-public/pypi/ttr.aws.utils.s3
Requires-Python: >=3.8
Requires-Dist: PyYAML==6.0
Requires-Dist: boto3==1.26.165
Requires-Dist: plac==1.3.5
Requires-Dist: python-dateutil==2.8.2
Requires-Dist: pytz
Requires-Dist: pendulum==2.1.2; extra == "test"
Requires-Dist: pytest==7.4.0; extra == "test"
Provides-Extra: test
